uncomplicated_port_forwarder/__init__.py
uncomplicated_port_forwarder/app.py
uncomplicated_port_forwarder/iptables.py
uncomplicated_port_forwarder/models/__init__.py
uncomplicated_port_forwarder/models/database.py
uncomplicated_port_forwarder/models/port_forward.py
uncomplicated_port_forwarder/models/upf.py
uncomplicated_port_forwarder/tests/__init__.py
uncomplicated_port_forwarder/tests/test_database.py
uncomplicated_port_forwarder/tests/test_port_forward.py
uncomplicated_port_forwarder/tests/test_upf.py
uncomplicated_port_forwarder/tests/test_utils.py
uncomplicated_port_forwarder/utils.py
upf-0.3.2.dist-info/LICENSE
upf-0.3.2.dist-info/METADATA
upf-0.3.2.dist-info/WHEEL
upf-0.3.2.dist-info/entry_points.txt
upf-0.3.2.dist-info/RECORD
