Metadata-Version: 2.1
Name: upf
Version: 0.3.2
Summary: Uncomplicated Port Forwarder (UPF)
License: Apache-2.0
Author: Bruno Bernard
Author-email: contact.brunobernard@gmail.com
Requires-Python: >=3.11,<4.0
Classifier: License :: OSI Approved :: Apache Software License
Classifier: Programming Language :: Python :: 3
Classifier: Programming Language :: Python :: 3.11
Requires-Dist: click (>=8.1.7,<9.0.0)
Requires-Dist: psutil (>=6.1.0,<7.0.0)
Project-URL: Homepage, https://github.com/eznix86/upf
